<?xml version="1.0" encoding="UTF-8" ?>
<extension type="package" version="3.5" method="upgrade">
<name>JL Like</name>
<packagename>jllike</packagename>
<author>JoomLine</author>
<creationDate>09.08.2019</creationDate>
<copyright>(C) 2012-2019 by Artem Zhukov, Arkadiy Sedelnikov and Vadim Kunicin(https://joomline.ru)</copyright>
<license>GNU/GPL: http://www.gnu.org/copyleft/gpl.html</license>
<authorEmail>sale@joomline.ru</authorEmail>
<authorUrl>https://joomline.ru</authorUrl>
<version>4.0.0</version>
<url>https://joomline.ru</url>
<packager>JoomLine.ru</packager>
<packagerurl>http://joomline.ru</packagerurl>
<description><p>Plugin allow integrate social buttons like into your joomla site.</p> <p>Donate plugin JL Like</p><div><iframe frameborder='0' allowtransparency='true' scrolling='no' src='https://joomline.ru/donateen.html' width='100%' height='800'></iframe></div></description>
<files>
        <folder type="plugin" id="jllike" group="content" client="site">jllike</folder>
        <folder type="plugin" id="jllikeads" group="adsmanagercontent" client="site">jllikeads</folder>
        <folder type="plugin" id="jllikejshop" group="jshoppingproducts" client="site">jllikejshop</folder>
		<folder type="plugin" id="jllike" group="k2" client="site">jllikek2</folder>
</files>
</extension>
